lektor_image_filter.py
lektor_image_filter-3.0.dist-info/LICENCE
lektor_image_filter-3.0.dist-info/METADATA
lektor_image_filter-3.0.dist-info/WHEEL
lektor_image_filter-3.0.dist-info/entry_points.txt
lektor_image_filter-3.0.dist-info/top_level.txt
lektor_image_filter-3.0.dist-info/RECORD
