Metadata-Version: 2.1
Name: lektor-image-filter
Version: 3.0
Summary: A filter to print the input image in different predefined image sizes.
Home-page: https://github.com/chaos-bodensee/lektor-image-filter.git
Author: L3D
Author-email: l3d@c3woc.de
License: MIT
Keywords: Lektor plugin image resize filter
Platform: UNKNOWN
Classifier: Framework :: Lektor
Classifier: Environment :: Plugins
License-File: LICENCE
